snl/Dialog.py
snl/Header.py
snl/IPTunnel.py
snl/MSRP.py
snl/Media.py
snl/Message.py
snl/Milenage.py
snl/Pcap.py
snl/SIPBNF.py
snl/Security.py
snl/Tags.py
snl/Timer.py
snl/Transaction.py
snl/Transport.py
snl/UA.py
snl/Utils.py
snl/__init__.py
snl-1.1.dist-info/METADATA
snl-1.1.dist-info/WHEEL
snl-1.1.dist-info/top_level.txt
snl-1.1.dist-info/RECORD
