Metadata-Version: 2.1
Name: snl
Version: 1.1
Summary: a SIP library
Home-page: https://github.com/edhinard/SIPandLove
License: UNKNOWN
Keywords: SIP development
Platform: posix
Classifier: Development Status :: 5 - Production/Stable
Classifier: Environment :: Console
Classifier: Intended Audience :: Developers
Classifier: Intended Audience :: Developers
Classifier: License :: OSI Approved :: MIT License
Classifier: Operating System :: POSIX :: Linux
Classifier: Programming Language :: Python :: 3.5
Classifier: Programming Language :: Python :: 3.6
Classifier: Programming Language :: Python :: 3.7
Requires-Python: >=3.5
Requires-Dist: pyparsing
